schematodes-1.0.0.dist-info/METADATA
schematodes-1.0.0.dist-info/WHEEL
schematodes-1.0.0.dist-info/license_files/LICENSE
schematodes/__init__.py
schematodes/__init__.pyi
schematodes/py.typed
schematodes/schematodes.cpython-38-powerpc64le-linux-gnu.so
schematodes-1.0.0.dist-info/RECORD
