Metadata-Version: 2.1
Name: schematodes
Version: 1.0.0
Classifier: Programming Language :: Rust
Classifier: Programming Language :: Python :: Implementation :: CPython
Classifier: Programming Language :: Python :: Implementation :: PyPy
License-File: LICENSE
Summary: A tool for expressing permutation symmetries in sets of tuples.
Author-email: Jordan Rozum <jrozum@binghamton.edu>
Requires-Python: >=3.7
